rpyutils/__init__.py
rpyutils/__main__.py
rpyutils/app.py
rpyutils/ex_prettifier.py
rpyutils/map_with_pbar.py
rpyutils/r_utils.py
rpyutils/rectangle.py
rpyutils/rectangle_utils.py
rpyutils/nb_utils/__init__.py
rpyutils/nb_utils/iframe_html_utils.py
rpyutils/nb_utils/jquery_datatables.py
rpyutils/nb_utils/jquery_datatables_template.py
rpyutils/nb_utils/misc_templates.py
rpyutils/nb_utils/pivottablejs.py
rpyutils/nb_utils/pivottablejs_template.py
rpyutils/nb_utils/sticky_borders.py
rpyutils/random_words/__init__.py
rpyutils/random_words/data_files/adjectives.json
rpyutils/random_words/data_files/names.json
rpyutils-0.1.4.dist-info/LICENSE
rpyutils-0.1.4.dist-info/METADATA
rpyutils-0.1.4.dist-info/WHEEL
rpyutils-0.1.4.dist-info/entry_points.txt
rpyutils-0.1.4.dist-info/top_level.txt
rpyutils-0.1.4.dist-info/RECORD
