Metadata-Version: 2.2
Name: rpyutils
Version: 0.1.4
Summary: My General Utils
Author-email: Reza <example@gmail.com>
License: MIT License
Project-URL: Homepage, https://github.com/Reza-esfandiarpoor/rpyutils
Project-URL: Documentation, https://docs.example.com
Keywords: utils,misc
Classifier: License :: OSI Approved :: MIT License
Classifier: Programming Language :: Python
Classifier: Programming Language :: Python :: 3
Requires-Python: >=3.8
License-File: LICENSE
Requires-Dist: rich>=12.0.0
Requires-Dist: tqdm
Requires-Dist: pyrootutils
Provides-Extra: dev
Requires-Dist: black; extra == "dev"
Requires-Dist: isort; extra == "dev"
Requires-Dist: sphinx; extra == "dev"
Requires-Dist: furo; extra == "dev"
Requires-Dist: sphinx_rtd_theme; extra == "dev"
